examples/basic.py
examples/fastapi.py
pydanja/__init__.py
pydanja/openapi.py
pydanja/py.typed
pydanja-0.1.32.dist-info/METADATA
pydanja-0.1.32.dist-info/WHEEL
pydanja-0.1.32.dist-info/top_level.txt
pydanja-0.1.32.dist-info/RECORD
