Metadata-Version: 2.4
Name: pydanja
Version: 0.1.32
Summary: JSON:API Support for Pydantic
Author-email: Chris Read <centurix@gmail.com>
License: MIT
Project-URL: homepage, https://github.com/Centurix/pydanja
Project-URL: repository, https://github.com/Centurix/pydanja
Project-URL: documentation, https://pydanja.readthedocs.io/en/latest/
Keywords: pydantic,jsonapi,json:api,openapi,fastapi
Classifier: Development Status :: 4 - Beta
Classifier: Environment :: Console
Classifier: Intended Audience :: Developers
Classifier: Natural Language :: English
Classifier: Operating System :: POSIX :: Linux
Classifier: Operating System :: MacOS
Classifier: Operating System :: Microsoft :: Windows
Classifier: Programming Language :: Python :: 3
Classifier: Topic :: File Formats :: JSON
Classifier: Topic :: File Formats :: JSON :: JSON Schema
Classifier: Topic :: Software Development :: Documentation
Classifier: Topic :: Software Development :: Libraries
Requires-Python: >=3.10
Requires-Dist: dpath>=2.1.6
Requires-Dist: pydantic>=2.10.2
